docusign_rooms/__init__.py
docusign_rooms/apis/__init__.py
docusign_rooms/apis/accounts_api.py
docusign_rooms/apis/activity_types_api.py
docusign_rooms/apis/closing_statuses_api.py
docusign_rooms/apis/contact_sides_api.py
docusign_rooms/apis/countries_api.py
docusign_rooms/apis/currencies_api.py
docusign_rooms/apis/documents_api.py
docusign_rooms/apis/e_sign_permission_profiles_api.py
docusign_rooms/apis/external_form_fill_sessions_api.py
docusign_rooms/apis/fields_api.py
docusign_rooms/apis/financing_types_api.py
docusign_rooms/apis/form_details_api.py
docusign_rooms/apis/form_group_forms_api.py
docusign_rooms/apis/form_groups_api.py
docusign_rooms/apis/form_libraries_api.py
docusign_rooms/apis/form_provider_associations_api.py
docusign_rooms/apis/offices_api.py
docusign_rooms/apis/origins_of_leads_api.py
docusign_rooms/apis/property_types_api.py
docusign_rooms/apis/regions_api.py
docusign_rooms/apis/roles_api.py
docusign_rooms/apis/room_contact_types_api.py
docusign_rooms/apis/room_envelopes_api.py
docusign_rooms/apis/room_folders_api.py
docusign_rooms/apis/room_templates_api.py
docusign_rooms/apis/rooms_api.py
docusign_rooms/apis/seller_decision_types_api.py
docusign_rooms/apis/special_circumstance_types_api.py
docusign_rooms/apis/states_api.py
docusign_rooms/apis/task_date_types_api.py
docusign_rooms/apis/task_list_templates_api.py
docusign_rooms/apis/task_lists_api.py
docusign_rooms/apis/task_responsibility_types_api.py
docusign_rooms/apis/task_statuses_api.py
docusign_rooms/apis/time_zones_api.py
docusign_rooms/apis/transaction_sides_api.py
docusign_rooms/apis/users_api.py
docusign_rooms/client/__init__.py
docusign_rooms/client/api_client.py
docusign_rooms/client/api_exception.py
docusign_rooms/client/api_response.py
docusign_rooms/client/configuration.py
docusign_rooms/client/auth/__init__.py
docusign_rooms/client/auth/oauth.py
docusign_rooms/models/__init__.py
docusign_rooms/models/access_level.py
docusign_rooms/models/account_status.py
docusign_rooms-1.3.0.dist-info/LICENSE
docusign_rooms-1.3.0.dist-info/METADATA
docusign_rooms-1.3.0.dist-info/WHEEL
docusign_rooms-1.3.0.dist-info/top_level.txt
docusign_rooms-1.3.0.dist-info/RECORD
