Metadata-Version: 2.1
Name: docusign-rooms
Version: 1.3.0
Summary: DocuSign Rooms API - v2
Home-page: 
Author-email: devcenter@docusign.com
Keywords: Swagger,DocuSign Rooms API - v2
License-File: LICENSE
